{
  "title": "Airgapped MicroShift Deployment",
  "description": "Learn to build offline-ready bootc images.",
  "backend": {
    "imageid": "ubuntu"
  },
  "interface": {
    "layout": "ide"
  },
  "details": {
    "intro": {
      "text": "intro/text.md",
      "foreground": "intro/foreground.sh",
      "background": "intro/background.sh"
    },
    "steps": [
      {
        "title": "Environment Overview",
        "text": "step1/text.md"
      }
    ],
    "finish": {
      "text": "finish/text.md"
    }
  }
}
